pathlib2_unicode/__init__.py
pathlib2_unicode/__version__.py
pathlib2_unicode-3.0.0.dist-info/LICENSE
pathlib2_unicode-3.0.0.dist-info/METADATA
pathlib2_unicode-3.0.0.dist-info/WHEEL
pathlib2_unicode-3.0.0.dist-info/top_level.txt
pathlib2_unicode-3.0.0.dist-info/RECORD
